ntqr/__init__.py
ntqr/alarms.py
ntqr/evaluations.py
ntqr/plots.py
ntqr/raxioms.py
ntqr/statistics.py
ntqr/testsketches.py
ntqr/r2/__init__.py
ntqr/r2/datasketches.py
ntqr/r2/evaluations.py
ntqr/r2/evaluators.py
ntqr/r2/examples.py
ntqr/r2/paxioms.py
ntqr/r2/plots.py
ntqr/r2/raxioms.py
ntqr/r2/uci_adult_20240415.py
ntqr/r3/__init__.py
ntqr/r3/evaluations.py
ntqr/r3/raxioms.py
ntqr-0.6.2.dist-info/licenses/LICENSE.txt
ntqr-0.6.2.dist-info/WHEEL
ntqr-0.6.2.dist-info/METADATA
ntqr-0.6.2.dist-info/RECORD
