Metadata-Version: 2.4
Name: ntqr
Version: 0.6.2
Summary: Tools for the logic of evaluation using unlabeled data
Keywords: evaluation,algebra,machine learning,logic,ai safety
Author-email: Andres Corrada-Emmanuel <andres.corrada@dataengines.com>, Walker Lee <walker.lee@dataengines.com>, Adam Sloat <adam.sloat@dataengines.com>
Classifier: Development Status :: 3 - Alpha
Classifier: Framework :: Jupyter
Classifier: Intended Audience :: Information Technology
Classifier: Intended Audience :: Science/Research
Classifier: License :: OSI Approved :: MIT License
Classifier: Natural Language :: English
Classifier: Topic :: Scientific/Engineering
Classifier: Topic :: Scientific/Engineering :: Artificial Intelligence
Classifier: Topic :: Scientific/Engineering :: Mathematics
License-File: LICENSE.txt
Requires-Dist: sympy>=1.13.2
Requires-Dist: typing_extensions>=4.12.2
Requires-Dist: matplotlib>=3.10.0
Requires-Dist: sphinx>=8.2.3 ; extra == "sphinx"
Requires-Dist: myst-parser>=4.0.0 ; extra == "sphinx"
Requires-Dist: myst-nb>=1.2.0 ; extra == "sphinx"
Requires-Dist: matplotlib>=3.10.0 ; extra == "sphinx"
Project-URL: Documentation, https://ntqr.readthedocs.org/en/latest
Project-URL: Home, https://github.com/andrescorrada/IntroductionToAlgebraicEvaluation/tree/main/python
Provides-Extra: sphinx
